anaplanConnector/__init__.py
anaplanConnector/auth.py
anaplanConnector/connector.py
anaplanConnector/createCerts.py
anaplanConnector/endpoints.py
anaplanConnector/file.py
anaplanConnector-0.1.2.dist-info/LICENSE
anaplanConnector-0.1.2.dist-info/METADATA
anaplanConnector-0.1.2.dist-info/WHEEL
anaplanConnector-0.1.2.dist-info/top_level.txt
anaplanConnector-0.1.2.dist-info/RECORD
