Metadata-Version: 2.1
Name: anaplanConnector
Version: 0.1.2
Summary: Python package to manage integrations with Anaplan.
Home-page: https://github.com/matt-budd/anaplan-connector
Author: Matt Budd
Author-email: mbudd@dialedsolutions.com
Project-URL: Bug Tracker, https://github.com/matt-budd/anaplan-connector/issues
Keywords: Anaplan connector
Classifier: Programming Language :: Python :: 3
Classifier: License :: OSI Approved :: MIT License
Classifier: Operating System :: OS Independent
Requires-Python: >=3.6
License-File: LICENSE
Requires-Dist: requests (>=2.27.1)
Requires-Dist: cryptography (>=3.1.1)
